secrets_guard/__init__.py
secrets_guard/__main__.py
secrets_guard/aes.py
secrets_guard/git.py
secrets_guard/keyring.py
secrets_guard/store.py
tests/__init__.py
tests/aes_tests.py
secrets_guard-0.19.dist-info/LICENSE
secrets_guard-0.19.dist-info/METADATA
secrets_guard-0.19.dist-info/WHEEL
secrets_guard-0.19.dist-info/entry_points.txt
secrets_guard-0.19.dist-info/top_level.txt
secrets_guard-0.19.dist-info/RECORD
