Metadata-Version: 2.1
Name: secrets-guard
Version: 0.19
Summary: Encrypts and decrypts private information
Home-page: https://github.com/Docheinstein/secrets-guard
Author: Stefano Dottore
Author-email: docheinstein@gmail.com
License: MIT
Keywords: pass password private key encrypt decrypt crypt
Requires-Python: >=3
License-File: LICENSE
Requires-Dist: pycryptodomex
Requires-Dist: gitpython
